devtools/__init__.py
devtools/build.py
devtools/create_environment.py
devtools/update_environment.py
devtools/upload_pypi.py
pyttman/__init__.py
pyttman/version.py
pyttman/clients/__init__.py
pyttman/clients/base.py
pyttman/clients/builtin/__init__.py
pyttman/clients/builtin/cli.py
pyttman/clients/builtin/script_client.py
pyttman/clients/community/__init__.py
pyttman/clients/community/discord/__init__.py
pyttman/clients/community/discord/client.py
pyttman/clients/community/discord/misc.py
pyttman/core/__init__.py
pyttman/core/ability.py
pyttman/core/containers.py
pyttman/core/decorators.py
pyttman/core/exceptions.py
pyttman/core/intent.py
pyttman/core/internals.py
pyttman/core/mixins.py
pyttman/core/entity_parsing/__init__.py
pyttman/core/entity_parsing/entity.py
pyttman/core/entity_parsing/fields.py
pyttman/core/entity_parsing/identifiers.py
pyttman/core/entity_parsing/parsers.py
pyttman/core/middleware/__init__.py
pyttman/core/middleware/routing.py
pyttman/core/parsing/__init__.py
pyttman/core/parsing/routing.py
pyttman/core/storage/__init__.py
pyttman/core/storage/basestorage.py
pyttman/testing/__init__.py
pyttman/testing/pyttman_test_case.py
pyttman/tools/__init__.py
pyttman/tools/logger/__init__.py
pyttman/tools/logger/logger.py
pyttman/tools/pyttmancli/__init__.py
pyttman/tools/pyttmancli/ability.py
pyttman/tools/pyttmancli/intents.py
pyttman/tools/pyttmancli/terraforming.py
pyttman/tools/scheduling/__init__.py
pyttman/tools/scheduling/components.py
pyttman/tools/scheduling/schedule.py
Pyttman-1.3.2.dist-info/LICENSE
Pyttman-1.3.2.dist-info/METADATA
Pyttman-1.3.2.dist-info/WHEEL
Pyttman-1.3.2.dist-info/entry_points.txt
Pyttman-1.3.2.dist-info/top_level.txt
Pyttman-1.3.2.dist-info/RECORD
