Metadata-Version: 2.1
Name: Pyttman
Version: 1.3.2
Summary: The Python chatbot framework with batteries included
Home-page: https://github.com/dotchetter/Pyttman
Author: Simon Olofsson
Author-email: simon@hashmap.se
License: MIT
Project-URL: Bug Tracker, https://github.com/dotchetter/Pyttman/issues
Project-URL: Changelog, https://github.com/dotchetter/Pyttman/blob/main/CHANGELOG.md
Classifier: License :: OSI Approved :: MIT License
Classifier: Programming Language :: Python :: 3 :: Only
Classifier: Programming Language :: Python :: 3.10
Classifier: Operating System :: OS Independent
Requires-Python: >=3.10
License-File: LICENSE
Requires-Dist: multidict
Requires-Dist: discord.py
Requires-Dist: requests
Requires-Dist: py7zr
Requires-Dist: ordered-set
